{
  "generatedAt": "2026-06-29T09:24:36Z",
  "seasonId": 10,
  "characters": [
    {
      "charId": 1000001,
      "name": "牧逸风",
      "sect": "剑宗",
      "t10w": 8297.8,
      "t10n": 7953.5,
      "t20w": 7323.4,
      "t20n": 7119.0,
      "t30w": 6899.8,
      "t30n": 6761.2,
      "top": 10175,
      "avg": 5786.6,
      "sum": 572874,
      "median": 5556.0,
      "threshold": 4848,
      "std": 904.2,
      "top10avg": 7953.5,
      "p25": 5195.5,
      "p75": 6045.5,
      "p90": 6720.8,
      "count": 99,
      "dist": {
        "9200": 2,
        "9000": 1,
        "8450": 1,
        "8250": 1,
        "7550": 1,
        "7400": 1,
        "6750": 2,
        "6700": 2,
        "6450": 1,
        "6350": 2,
        "6250": 1,
        "6200": 1,
        "6100": 2,
        "6050": 6,
        "6000": 15,
        "5750": 1,
        "5700": 1,
        "5650": 2,
        "5600": 4,
        "5550": 3,
        "5500": 3,
        "5450": 3,
        "5400": 4,
        "5350": 4,
        "5300": 4,
        "5250": 4,
        "5200": 1,
        "5150": 3,
        "5100": 5,
        "5050": 2,
        "5000": 1,
        "4950": 5,
        "4900": 2,
        "4850": 7,
        "4800": 1
      },
      "games": 2444,
      "avgGameScore": 24.9
    },
    {
      "charId": 1000002,
      "name": "炎雪",
      "sect": "剑宗",
      "t10w": 7415.8,
      "t10n": 7245.0,
      "t20w": 6846.4,
      "t20n": 6736.0,
      "t30w": 6577.4,
      "t30n": 6501.4,
      "top": 8285,
      "avg": 5677.0,
      "sum": 562026,
      "median": 5497.0,
      "threshold": 4878,
      "std": 700.7,
      "top10avg": 7245.0,
      "p25": 5113.5,
      "p75": 6036.0,
      "p90": 6481.0,
      "count": 99,
      "dist": {
        "8200": 1,
        "8150": 1,
        "7700": 1,
        "7450": 1,
        "7250": 1,
        "6800": 2,
        "6750": 1,
        "6600": 1,
        "6550": 1,
        "6450": 1,
        "6400": 1,
        "6300": 1,
        "6200": 1,
        "6150": 2,
        "6100": 3,
        "6050": 3,
        "6000": 9,
        "5950": 1,
        "5900": 1,
        "5850": 2,
        "5800": 1,
        "5750": 3,
        "5700": 3,
        "5650": 5,
        "5550": 1,
        "5500": 1,
        "5450": 2,
        "5400": 5,
        "5350": 4,
        "5300": 1,
        "5250": 5,
        "5200": 1,
        "5150": 5,
        "5100": 2,
        "5050": 7,
        "5000": 5,
        "4950": 6,
        "4900": 2,
        "4850": 5
      },
      "games": 3857,
      "avgGameScore": 17.0
    },
    {
      "charId": 1000003,
      "name": "龙瑶",
      "sect": "剑宗",
      "t10w": 6601.6,
      "t10n": 6359.1,
      "t20w": 6092.2,
      "t20n": 5927.4,
      "t30w": 5704.7,
      "t30n": 5581.0,
      "top": 8470,
      "avg": 4583.3,
      "sum": 453747,
      "median": 4278.0,
      "threshold": 3811,
      "std": 779.4,
      "top10avg": 6359.1,
      "p25": 4007.0,
      "p75": 4837.5,
      "p90": 5898.6,
      "count": 99,
      "dist": {
        "7300": 1,
        "6700": 1,
        "6650": 1,
        "6300": 1,
        "6150": 1,
        "6100": 1,
        "6050": 3,
        "6000": 1,
        "5850": 1,
        "5800": 1,
        "5700": 2,
        "5550": 1,
        "5300": 1,
        "5250": 1,
        "5200": 1,
        "5150": 3,
        "5000": 1,
        "4950": 1,
        "4900": 1,
        "4800": 3,
        "4750": 3,
        "4600": 1,
        "4550": 2,
        "4500": 8,
        "4450": 4,
        "4350": 1,
        "4300": 2,
        "4250": 4,
        "4200": 3,
        "4150": 4,
        "4100": 4,
        "4050": 9,
        "4000": 3,
        "3950": 7,
        "3900": 4,
        "3850": 7,
        "3800": 6
      },
      "games": 2409,
      "avgGameScore": 22.8
    },
    {
      "charId": 1000004,
      "name": "林小月",
      "sect": "剑宗",
      "t10w": 6447.4,
      "t10n": 6113.1,
      "t20w": 5820.2,
      "t20n": 5615.4,
      "t30w": 5406.8,
      "t30n": 5259.1,
      "top": 8852,
      "avg": 4240.3,
      "sum": 419792,
      "median": 3957.0,
      "threshold": 3462,
      "std": 805.0,
      "top10avg": 6113.1,
      "p25": 3686.5,
      "p75": 4547.0,
      "p90": 5455.4,
      "count": 99,
      "dist": {
        "6950": 1,
        "6650": 1,
        "6500": 1,
        "6350": 1,
        "5950": 1,
        "5900": 1,
        "5800": 1,
        "5750": 1,
        "5550": 1,
        "5500": 1,
        "5400": 1,
        "5350": 1,
        "5300": 2,
        "5200": 1,
        "5150": 1,
        "4850": 2,
        "4800": 1,
        "4750": 2,
        "4550": 4,
        "4500": 3,
        "4400": 2,
        "4250": 2,
        "4150": 6,
        "4100": 3,
        "4050": 3,
        "4000": 3,
        "3950": 4,
        "3900": 2,
        "3850": 4,
        "3800": 3,
        "3750": 8,
        "3700": 5,
        "3650": 3,
        "3600": 3,
        "3550": 5,
        "3500": 5,
        "3450": 10
      },
      "games": 1489,
      "avgGameScore": 32.0
    },
    {
      "charId": 1000005,
      "name": "陆剑心",
      "sect": "剑宗",
      "t10w": 6009.1,
      "t10n": 5896.8,
      "t20w": 5587.9,
      "t20n": 5506.3,
      "t30w": 5345.9,
      "t30n": 5280.4,
      "top": 6618,
      "avg": 4477.4,
      "sum": 443262,
      "median": 4299.0,
      "threshold": 3776,
      "std": 628.5,
      "top10avg": 5896.8,
      "p25": 4008.5,
      "p75": 4836.5,
      "p90": 5299.8,
      "count": 99,
      "dist": {
        "6300": 2,
        "6100": 1,
        "6050": 1,
        "5950": 1,
        "5750": 1,
        "5650": 1,
        "5600": 1,
        "5550": 1,
        "5450": 1,
        "5250": 1,
        "5200": 2,
        "5150": 1,
        "5050": 4,
        "5000": 1,
        "4950": 3,
        "4900": 2,
        "4850": 1,
        "4750": 2,
        "4700": 1,
        "4650": 2,
        "4600": 1,
        "4550": 3,
        "4500": 2,
        "4450": 2,
        "4400": 4,
        "4350": 3,
        "4300": 4,
        "4250": 5,
        "4200": 2,
        "4150": 2,
        "4100": 8,
        "4050": 4,
        "4000": 5,
        "3950": 3,
        "3900": 6,
        "3850": 2,
        "3800": 8,
        "3750": 5
      },
      "games": 2397,
      "avgGameScore": 22.4
    },
    {
      "charId": 1000006,
      "name": "黎承云",
      "sect": "剑宗",
      "t10w": 6869.1,
      "t10n": 6672.5,
      "t20w": 6413.4,
      "t20n": 6295.6,
      "t30w": 6098.2,
      "t30n": 6001.6,
      "top": 8037,
      "avg": 4941.2,
      "sum": 489183,
      "median": 4553.0,
      "threshold": 4084,
      "std": 811.7,
      "top10avg": 6672.5,
      "p25": 4352.5,
      "p75": 5471.5,
      "p90": 6063.8,
      "count": 99,
      "dist": {
        "7800": 1,
        "7450": 1,
        "7100": 1,
        "6650": 1,
        "6500": 2,
        "6150": 2,
        "6100": 1,
        "6050": 3,
        "6000": 3,
        "5900": 1,
        "5800": 2,
        "5700": 1,
        "5650": 1,
        "5600": 1,
        "5500": 3,
        "5450": 2,
        "5300": 1,
        "5250": 1,
        "5200": 1,
        "5100": 3,
        "5050": 1,
        "5000": 1,
        "4950": 1,
        "4900": 2,
        "4850": 3,
        "4800": 2,
        "4700": 2,
        "4650": 2,
        "4600": 2,
        "4550": 2,
        "4500": 3,
        "4450": 12,
        "4400": 4,
        "4350": 6,
        "4300": 7,
        "4250": 2,
        "4200": 5,
        "4150": 3,
        "4100": 5,
        "4050": 2
      },
      "games": 3567,
      "avgGameScore": 22.7
    },
    {
      "charId": 2000001,
      "name": "谭舒雁",
      "sect": "七星",
      "t10w": 7419.5,
      "t10n": 7122.8,
      "t20w": 6746.6,
      "t20n": 6586.8,
      "t30w": 6433.8,
      "t30n": 6315.2,
      "top": 9160,
      "avg": 5350.6,
      "sum": 529709,
      "median": 5159.0,
      "threshold": 4526,
      "std": 781.5,
      "top10avg": 7122.8,
      "p25": 4747.5,
      "p75": 5750.0,
      "p90": 6164.2,
      "count": 99,
      "dist": {
        "7700": 1,
        "7550": 1,
        "7500": 2,
        "7350": 1,
        "7250": 2,
        "6600": 1,
        "6200": 1,
        "6150": 2,
        "6050": 4,
        "6000": 4,
        "5950": 2,
        "5900": 3,
        "5800": 1,
        "5650": 2,
        "5600": 4,
        "5550": 1,
        "5500": 1,
        "5450": 2,
        "5400": 2,
        "5350": 2,
        "5300": 4,
        "5250": 3,
        "5200": 1,
        "5150": 4,
        "5100": 2,
        "5050": 2,
        "5000": 2,
        "4950": 3,
        "4900": 3,
        "4850": 2,
        "4800": 4,
        "4750": 5,
        "4700": 1,
        "4650": 6,
        "4600": 4,
        "4550": 8,
        "4500": 6
      },
      "games": 2571,
      "avgGameScore": 18.8
    },
    {
      "charId": 2000002,
      "name": "炎尘",
      "sect": "七星",
      "t10w": 5726.0,
      "t10n": 5557.4,
      "t20w": 5264.9,
      "t20n": 5159.1,
      "t30w": 4963.1,
      "t30n": 4881.7,
      "top": 6666,
      "avg": 4095.6,
      "sum": 405465,
      "median": 3890.0,
      "threshold": 3457,
      "std": 636.8,
      "top10avg": 5557.4,
      "p25": 3616.5,
      "p75": 4325.5,
      "p90": 4944.8,
      "count": 99,
      "dist": {
        "6200": 1,
        "6000": 3,
        "5750": 1,
        "5250": 1,
        "5150": 1,
        "5100": 1,
        "4950": 2,
        "4900": 1,
        "4850": 2,
        "4800": 1,
        "4750": 2,
        "4700": 1,
        "4650": 1,
        "4600": 1,
        "4550": 1,
        "4450": 1,
        "4350": 3,
        "4300": 3,
        "4250": 1,
        "4200": 5,
        "4150": 4,
        "4050": 2,
        "4000": 2,
        "3950": 4,
        "3900": 4,
        "3850": 3,
        "3800": 4,
        "3750": 3,
        "3700": 4,
        "3650": 6,
        "3600": 8,
        "3550": 9,
        "3500": 10,
        "3450": 3
      },
      "games": 1589,
      "avgGameScore": 23.5
    },
    {
      "charId": 2000003,
      "name": "曜灵",
      "sect": "七星",
      "t10w": 6568.5,
      "t10n": 6234.4,
      "t20w": 5901.4,
      "t20n": 5705.3,
      "t30w": 5491.6,
      "t30n": 5346.6,
      "top": 8841,
      "avg": 4409.5,
      "sum": 436541,
      "median": 4136.0,
      "threshold": 3670,
      "std": 798.4,
      "top10avg": 6234.4,
      "p25": 3831.0,
      "p75": 4602.0,
      "p90": 5489.6,
      "count": 99,
      "dist": {
        "8150": 1,
        "7400": 1,
        "6600": 1,
        "6000": 2,
        "5700": 1,
        "5650": 1,
        "5600": 1,
        "5550": 1,
        "5500": 1,
        "5450": 1,
        "5400": 1,
        "5250": 1,
        "5200": 1,
        "5150": 2,
        "5050": 2,
        "4950": 1,
        "4900": 1,
        "4800": 1,
        "4750": 1,
        "4650": 1,
        "4600": 2,
        "4550": 3,
        "4500": 1,
        "4450": 5,
        "4400": 4,
        "4350": 1,
        "4300": 2,
        "4250": 4,
        "4200": 1,
        "4150": 3,
        "4100": 5,
        "4050": 5,
        "4000": 2,
        "3950": 2,
        "3900": 6,
        "3850": 4,
        "3800": 8,
        "3750": 7,
        "3700": 6,
        "3650": 5
      },
      "games": 2050,
      "avgGameScore": 29.1
    },
    {
      "charId": 2000004,
      "name": "姜袭明",
      "sect": "七星",
      "t10w": 6725.3,
      "t10n": 6569.6,
      "t20w": 6361.9,
      "t20n": 6264.0,
      "t30w": 6089.0,
      "t30n": 6013.4,
      "top": 7628,
      "avg": 5073.4,
      "sum": 502271,
      "median": 4849.0,
      "threshold": 4287,
      "std": 737.8,
      "top10avg": 6569.6,
      "p25": 4480.0,
      "p75": 5514.5,
      "p90": 6060.6,
      "count": 99,
      "dist": {
        "7550": 1,
        "7500": 1,
        "7000": 1,
        "6600": 1,
        "6500": 1,
        "6150": 1,
        "6050": 5,
        "6000": 6,
        "5850": 1,
        "5800": 1,
        "5650": 1,
        "5600": 2,
        "5550": 1,
        "5500": 4,
        "5400": 2,
        "5350": 1,
        "5300": 1,
        "5250": 2,
        "5200": 4,
        "5050": 5,
        "5000": 3,
        "4950": 1,
        "4900": 2,
        "4850": 1,
        "4800": 2,
        "4750": 2,
        "4700": 4,
        "4650": 2,
        "4600": 2,
        "4550": 4,
        "4500": 8,
        "4450": 5,
        "4400": 1,
        "4350": 11,
        "4300": 4,
        "4250": 5
      },
      "games": 2624,
      "avgGameScore": 27.7
    },
    {
      "charId": 2000005,
      "name": "吴策",
      "sect": "七星",
      "t10w": 7145.9,
      "t10n": 6931.6,
      "t20w": 6556.2,
      "t20n": 6422.3,
      "t30w": 6200.6,
      "t30n": 6101.1,
      "top": 8323,
      "avg": 5019.3,
      "sum": 496914,
      "median": 4714.0,
      "threshold": 4170,
      "std": 858.7,
      "top10avg": 6931.6,
      "p25": 4356.5,
      "p75": 5454.0,
      "p90": 6095.2,
      "count": 99,
      "dist": {
        "7800": 1,
        "7650": 1,
        "7400": 1,
        "7350": 1,
        "7150": 1,
        "6900": 1,
        "6250": 1,
        "6200": 2,
        "6150": 1,
        "6050": 3,
        "6000": 3,
        "5900": 1,
        "5650": 1,
        "5600": 3,
        "5550": 1,
        "5500": 3,
        "5400": 1,
        "5350": 3,
        "5300": 3,
        "5250": 2,
        "5200": 1,
        "5050": 1,
        "5000": 2,
        "4900": 2,
        "4800": 3,
        "4750": 3,
        "4700": 6,
        "4650": 1,
        "4600": 4,
        "4550": 4,
        "4500": 5,
        "4450": 3,
        "4400": 4,
        "4350": 1,
        "4300": 3,
        "4250": 8,
        "4200": 4,
        "4150": 10
      },
      "games": 2932,
      "avgGameScore": 22.2
    },
    {
      "charId": 2000006,
      "name": "风绪",
      "sect": "七星",
      "t10w": 7741.3,
      "t10n": 7384.7,
      "t20w": 7017.9,
      "t20n": 6813.1,
      "t30w": 6693.5,
      "t30n": 6554.8,
      "top": 10174,
      "avg": 5608.5,
      "sum": 555239,
      "median": 5451.0,
      "threshold": 4673,
      "std": 824.4,
      "top10avg": 7384.7,
      "p25": 4890.0,
      "p75": 6042.5,
      "p90": 6540.0,
      "count": 99,
      "dist": {
        "9200": 1,
        "7800": 1,
        "7550": 1,
        "7400": 1,
        "7300": 1,
        "7250": 1,
        "7000": 1,
        "6750": 1,
        "6700": 1,
        "6600": 1,
        "6500": 1,
        "6450": 1,
        "6400": 1,
        "6200": 2,
        "6150": 1,
        "6050": 6,
        "6000": 13,
        "5950": 1,
        "5900": 1,
        "5850": 1,
        "5800": 2,
        "5750": 3,
        "5600": 2,
        "5550": 2,
        "5500": 2,
        "5450": 1,
        "5400": 2,
        "5350": 2,
        "5300": 1,
        "5250": 2,
        "5200": 2,
        "5150": 2,
        "5100": 2,
        "5050": 2,
        "5000": 3,
        "4950": 3,
        "4900": 1,
        "4850": 8,
        "4800": 3,
        "4750": 7,
        "4700": 5,
        "4650": 4
      },
      "games": 2615,
      "avgGameScore": 30.7
    },
    {
      "charId": 3000001,
      "name": "吾行之",
      "sect": "五行",
      "t10w": 6497.2,
      "t10n": 6250.0,
      "t20w": 5875.6,
      "t20n": 5735.6,
      "t30w": 5524.5,
      "t30n": 5414.2,
      "top": 7890,
      "avg": 4541.3,
      "sum": 449593,
      "median": 4289.0,
      "threshold": 3815,
      "std": 728.6,
      "top10avg": 6250.0,
      "p25": 4067.0,
      "p75": 4769.0,
      "p90": 5358.8,
      "count": 99,
      "dist": {
        "7850": 1,
        "6950": 1,
        "6400": 1,
        "6100": 1,
        "6050": 2,
        "6000": 1,
        "5800": 1,
        "5700": 1,
        "5400": 1,
        "5300": 1,
        "5250": 4,
        "5200": 1,
        "5150": 2,
        "5100": 1,
        "5050": 1,
        "4950": 2,
        "4850": 1,
        "4750": 3,
        "4700": 1,
        "4600": 2,
        "4550": 3,
        "4500": 8,
        "4450": 3,
        "4400": 3,
        "4350": 1,
        "4300": 1,
        "4250": 3,
        "4200": 4,
        "4150": 6,
        "4100": 10,
        "4050": 6,
        "4000": 4,
        "3950": 1,
        "3900": 5,
        "3850": 7,
        "3800": 5
      },
      "games": 2364,
      "avgGameScore": 29.6
    },
    {
      "charId": 3000002,
      "name": "杜伶鸳",
      "sect": "五行",
      "t10w": 6555.6,
      "t10n": 6207.4,
      "t20w": 5861.2,
      "t20n": 5637.9,
      "t30w": 5440.5,
      "t30n": 5283.7,
      "top": 9226,
      "avg": 4391.7,
      "sum": 434782,
      "median": 4170.0,
      "threshold": 3679,
      "std": 739.1,
      "top10avg": 6207.4,
      "p25": 3840.0,
      "p75": 4543.5,
      "p90": 5568.0,
      "count": 99,
      "dist": {
        "6700": 1,
        "6600": 1,
        "6500": 2,
        "6050": 2,
        "6000": 2,
        "5800": 1,
        "5700": 1,
        "5500": 1,
        "5450": 1,
        "5050": 4,
        "4950": 1,
        "4850": 1,
        "4800": 1,
        "4750": 1,
        "4700": 1,
        "4650": 1,
        "4550": 2,
        "4500": 8,
        "4450": 1,
        "4400": 2,
        "4300": 3,
        "4250": 3,
        "4200": 3,
        "4150": 13,
        "4100": 3,
        "4050": 3,
        "4000": 1,
        "3950": 1,
        "3900": 3,
        "3850": 5,
        "3800": 6,
        "3750": 4,
        "3700": 10,
        "3650": 6
      },
      "games": 2510,
      "avgGameScore": 28.7
    },
    {
      "charId": 3000003,
      "name": "花沁蕊",
      "sect": "五行",
      "t10w": 6088.3,
      "t10n": 5897.8,
      "t20w": 5491.1,
      "t20n": 5367.4,
      "t30w": 5137.4,
      "t30n": 5046.8,
      "top": 7068,
      "avg": 4253.2,
      "sum": 421069,
      "median": 4103.0,
      "threshold": 3610,
      "std": 672.4,
      "top10avg": 5897.8,
      "p25": 3787.0,
      "p75": 4398.0,
      "p90": 5122.2,
      "count": 99,
      "dist": {
        "6450": 1,
        "6350": 1,
        "6200": 1,
        "6150": 2,
        "6050": 1,
        "5600": 1,
        "5400": 1,
        "5250": 1,
        "5150": 1,
        "5100": 1,
        "5050": 1,
        "5000": 1,
        "4950": 1,
        "4900": 1,
        "4700": 1,
        "4650": 2,
        "4600": 1,
        "4550": 1,
        "4450": 2,
        "4400": 3,
        "4350": 5,
        "4300": 2,
        "4250": 4,
        "4200": 5,
        "4150": 4,
        "4100": 5,
        "4050": 2,
        "4000": 2,
        "3950": 1,
        "3900": 4,
        "3850": 4,
        "3800": 11,
        "3750": 2,
        "3700": 9,
        "3650": 8,
        "3600": 6
      },
      "games": 2199,
      "avgGameScore": 24.5
    },
    {
      "charId": 3000004,
      "name": "慕虎",
      "sect": "五行",
      "t10w": 5741.1,
      "t10n": 5579.2,
      "t20w": 5282.1,
      "t20n": 5177.1,
      "t30w": 4993.0,
      "t30n": 4909.9,
      "top": 6715,
      "avg": 4168.5,
      "sum": 412677,
      "median": 4011.0,
      "threshold": 3565,
      "std": 598.1,
      "top10avg": 5579.2,
      "p25": 3711.5,
      "p75": 4380.5,
      "p90": 5001.6,
      "count": 99,
      "dist": {
        "6050": 2,
        "6000": 1,
        "5550": 2,
        "5450": 1,
        "5350": 1,
        "5250": 2,
        "5050": 1,
        "4950": 2,
        "4850": 2,
        "4750": 1,
        "4700": 2,
        "4650": 1,
        "4600": 2,
        "4500": 2,
        "4450": 2,
        "4400": 1,
        "4300": 2,
        "4200": 4,
        "4150": 1,
        "4100": 5,
        "4050": 8,
        "4000": 8,
        "3950": 5,
        "3900": 2,
        "3850": 4,
        "3800": 2,
        "3750": 4,
        "3700": 5,
        "3650": 6,
        "3600": 9,
        "3550": 9
      },
      "games": 1790,
      "avgGameScore": 25.1
    },
    {
      "charId": 3000005,
      "name": "南宫生",
      "sect": "五行",
      "t10w": 6493.8,
      "t10n": 6079.9,
      "t20w": 5645.2,
      "t20n": 5423.8,
      "t30w": 5242.6,
      "t30n": 5080.5,
      "top": 9076,
      "avg": 4134.0,
      "sum": 409270,
      "median": 3817.0,
      "threshold": 3386,
      "std": 794.4,
      "top10avg": 6079.9,
      "p25": 3599.0,
      "p75": 4396.0,
      "p90": 4921.0,
      "count": 99,
      "dist": {
        "7150": 1,
        "7100": 1,
        "6050": 3,
        "6000": 2,
        "5950": 1,
        "5350": 1,
        "4900": 3,
        "4850": 2,
        "4700": 2,
        "4650": 3,
        "4600": 2,
        "4500": 1,
        "4450": 1,
        "4400": 2,
        "4350": 1,
        "4300": 1,
        "4250": 1,
        "4200": 2,
        "4150": 4,
        "4100": 3,
        "4050": 3,
        "4000": 4,
        "3900": 3,
        "3850": 1,
        "3800": 3,
        "3750": 6,
        "3700": 8,
        "3650": 5,
        "3600": 4,
        "3550": 6,
        "3500": 5,
        "3450": 3,
        "3400": 8,
        "3350": 3
      },
      "games": 1851,
      "avgGameScore": 35.9
    },
    {
      "charId": 3000006,
      "name": "祁忘忧",
      "sect": "五行",
      "t10w": 6203.3,
      "t10n": 5992.9,
      "t20w": 5663.1,
      "t20n": 5527.9,
      "t30w": 5319.6,
      "t30n": 5218.3,
      "top": 7583,
      "avg": 4322.8,
      "sum": 427962,
      "median": 4131.0,
      "threshold": 3595,
      "std": 717.3,
      "top10avg": 5992.9,
      "p25": 3783.0,
      "p75": 4574.0,
      "p90": 5470.2,
      "count": 99,
      "dist": {
        "6800": 1,
        "6350": 1,
        "6050": 2,
        "6000": 2,
        "5850": 1,
        "5650": 1,
        "5500": 1,
        "5450": 2,
        "5350": 1,
        "5200": 1,
        "5100": 1,
        "4900": 4,
        "4850": 2,
        "4750": 1,
        "4600": 2,
        "4550": 6,
        "4500": 3,
        "4400": 1,
        "4300": 2,
        "4250": 1,
        "4200": 3,
        "4150": 8,
        "4100": 4,
        "4050": 3,
        "4000": 6,
        "3950": 3,
        "3900": 3,
        "3850": 4,
        "3800": 2,
        "3750": 4,
        "3700": 5,
        "3650": 5,
        "3600": 10,
        "3550": 3
      },
      "games": 1812,
      "avgGameScore": 38.2
    },
    {
      "charId": 4000001,
      "name": "小布",
      "sect": "锻玄",
      "t10w": 6109.8,
      "t10n": 5755.5,
      "t20w": 5345.9,
      "t20n": 5139.6,
      "t30w": 4975.9,
      "t30n": 4830.5,
      "top": 8454,
      "avg": 3952.3,
      "sum": 391274,
      "median": 3684.0,
      "threshold": 3342,
      "std": 770.7,
      "top10avg": 5755.5,
      "p25": 3431.0,
      "p75": 4245.5,
      "p90": 4838.2,
      "count": 99,
      "dist": {
        "8200": 1,
        "6300": 1,
        "6000": 1,
        "5800": 1,
        "5650": 1,
        "5400": 1,
        "5100": 1,
        "5000": 1,
        "4950": 1,
        "4900": 1,
        "4800": 1,
        "4700": 2,
        "4550": 1,
        "4450": 2,
        "4350": 2,
        "4300": 2,
        "4250": 4,
        "4200": 2,
        "4150": 2,
        "4100": 1,
        "4050": 3,
        "4000": 2,
        "3950": 2,
        "3900": 1,
        "3850": 4,
        "3800": 2,
        "3750": 1,
        "3700": 2,
        "3650": 4,
        "3600": 5,
        "3550": 2,
        "3500": 8,
        "3450": 6,
        "3400": 10,
        "3350": 14,
        "3300": 4
      },
      "games": 1559,
      "avgGameScore": 31.5
    },
    {
      "charId": 4000002,
      "name": "屠馗",
      "sect": "锻玄",
      "t10w": 6635.0,
      "t10n": 6470.3,
      "t20w": 6278.1,
      "t20n": 6171.5,
      "t30w": 5930.8,
      "t30n": 5841.0,
      "top": 7702,
      "avg": 4783.1,
      "sum": 473529,
      "median": 4508.0,
      "threshold": 3926,
      "std": 801.7,
      "top10avg": 6470.3,
      "p25": 4189.5,
      "p75": 5174.0,
      "p90": 6049.4,
      "count": 99,
      "dist": {
        "7400": 1,
        "7150": 1,
        "6750": 1,
        "6400": 1,
        "6250": 2,
        "6100": 1,
        "6050": 3,
        "6000": 5,
        "5850": 1,
        "5700": 1,
        "5650": 2,
        "5550": 1,
        "5450": 1,
        "5300": 1,
        "5250": 1,
        "5200": 2,
        "5100": 1,
        "5000": 4,
        "4950": 1,
        "4800": 1,
        "4750": 2,
        "4700": 2,
        "4650": 3,
        "4600": 2,
        "4550": 6,
        "4500": 3,
        "4450": 3,
        "4400": 3,
        "4350": 4,
        "4300": 2,
        "4250": 4,
        "4200": 5,
        "4150": 6,
        "4100": 5,
        "4050": 8,
        "4000": 7,
        "3950": 1,
        "3900": 1
      },
      "games": 2555,
      "avgGameScore": 28.5
    },
    {
      "charId": 4000003,
      "name": "叶冥冥",
      "sect": "锻玄",
      "t10w": 6532.2,
      "t10n": 6287.3,
      "t20w": 6003.9,
      "t20n": 5851.6,
      "t30w": 5715.2,
      "t30n": 5605.5,
      "top": 8293,
      "avg": 4816.9,
      "sum": 476871,
      "median": 4612.0,
      "threshold": 4156,
      "std": 634.6,
      "top10avg": 6287.3,
      "p25": 4323.0,
      "p75": 5101.5,
      "p90": 5829.6,
      "count": 99,
      "dist": {
        "7050": 1,
        "6750": 1,
        "6500": 1,
        "6250": 1,
        "6200": 2,
        "6050": 1,
        "5950": 1,
        "5900": 1,
        "5800": 2,
        "5750": 1,
        "5400": 2,
        "5300": 2,
        "5250": 3,
        "5200": 3,
        "5150": 1,
        "5100": 2,
        "5050": 2,
        "5000": 3,
        "4950": 3,
        "4850": 2,
        "4800": 4,
        "4750": 3,
        "4700": 3,
        "4650": 3,
        "4600": 2,
        "4550": 5,
        "4500": 6,
        "4450": 4,
        "4400": 3,
        "4350": 3,
        "4300": 5,
        "4250": 8,
        "4200": 7,
        "4150": 8
      },
      "games": 2919,
      "avgGameScore": 23.3
    },
    {
      "charId": 4000004,
      "name": "姬方生",
      "sect": "锻玄",
      "t10w": 6319.8,
      "t10n": 6218.3,
      "t20w": 6007.6,
      "t20n": 5926.1,
      "t30w": 5748.1,
      "t30n": 5682.4,
      "top": 7015,
      "avg": 4870.8,
      "sum": 482214,
      "median": 4675.0,
      "threshold": 4237,
      "std": 623.7,
      "top10avg": 6218.3,
      "p25": 4347.0,
      "p75": 5166.0,
      "p90": 6000.0,
      "count": 99,
      "dist": {
        "6850": 1,
        "6550": 1,
        "6300": 1,
        "6100": 2,
        "6050": 3,
        "6000": 3,
        "5750": 1,
        "5700": 1,
        "5600": 3,
        "5550": 2,
        "5400": 1,
        "5350": 2,
        "5300": 2,
        "5200": 1,
        "5150": 1,
        "5100": 3,
        "5050": 1,
        "5000": 2,
        "4950": 2,
        "4900": 3,
        "4850": 1,
        "4800": 5,
        "4750": 2,
        "4700": 3,
        "4650": 4,
        "4600": 7,
        "4550": 2,
        "4500": 4,
        "4450": 3,
        "4400": 1,
        "4350": 5,
        "4300": 9,
        "4250": 15,
        "4200": 2
      },
      "games": 2821,
      "avgGameScore": 19.8
    },
    {
      "charId": 4000005,
      "name": "李㵘",
      "sect": "锻玄",
      "t10w": 6705.2,
      "t10n": 6566.2,
      "t20w": 6324.4,
      "t20n": 6233.9,
      "t30w": 5966.1,
      "t30n": 5883.5,
      "top": 7407,
      "avg": 4820.2,
      "sum": 477199,
      "median": 4524.0,
      "threshold": 3985,
      "std": 811.3,
      "top10avg": 6566.2,
      "p25": 4194.0,
      "p75": 5152.5,
      "p90": 6017.0,
      "count": 99,
      "dist": {
        "7050": 1,
        "7000": 2,
        "6750": 2,
        "6400": 1,
        "6250": 1,
        "6150": 1,
        "6050": 1,
        "6000": 6,
        "5950": 1,
        "5850": 1,
        "5800": 1,
        "5650": 1,
        "5550": 2,
        "5350": 2,
        "5250": 1,
        "5150": 1,
        "5100": 1,
        "5000": 2,
        "4900": 3,
        "4850": 4,
        "4800": 1,
        "4750": 2,
        "4700": 1,
        "4650": 1,
        "4600": 3,
        "4550": 4,
        "4500": 3,
        "4450": 4,
        "4400": 6,
        "4350": 3,
        "4300": 2,
        "4250": 5,
        "4200": 3,
        "4150": 6,
        "4100": 7,
        "4050": 3,
        "4000": 7,
        "3950": 3
      },
      "games": 2018,
      "avgGameScore": 34.1
    },
    {
      "charId": 4000006,
      "name": "聆羽",
      "sect": "锻玄",
      "t10w": 7422.9,
      "t10n": 7107.0,
      "t20w": 6742.6,
      "t20n": 6579.2,
      "t30w": 6498.4,
      "t30n": 6387.1,
      "top": 9288,
      "avg": 5397.7,
      "sum": 534371,
      "median": 5133.0,
      "threshold": 4473,
      "std": 845.3,
      "top10avg": 7107.0,
      "p25": 4733.5,
      "p75": 6008.5,
      "p90": 6100.2,
      "count": 99,
      "dist": {
        "9100": 1,
        "8200": 1,
        "7550": 1,
        "7200": 1,
        "7000": 1,
        "6750": 1,
        "6450": 1,
        "6350": 1,
        "6150": 1,
        "6100": 1,
        "6050": 5,
        "6000": 14,
        "5900": 3,
        "5800": 2,
        "5750": 1,
        "5700": 2,
        "5650": 1,
        "5600": 1,
        "5550": 1,
        "5500": 1,
        "5400": 2,
        "5350": 2,
        "5300": 2,
        "5200": 1,
        "5100": 2,
        "5050": 5,
        "5000": 2,
        "4950": 2,
        "4850": 4,
        "4800": 6,
        "4750": 3,
        "4700": 5,
        "4650": 3,
        "4600": 3,
        "4550": 3,
        "4500": 9,
        "4450": 4
      },
      "games": 2946,
      "avgGameScore": 28.6
    },
    {
      "charId": -1,
      "name": "随机",
      "sect": "随机",
      "t10w": 7223.8,
      "t10n": 6908.9,
      "t20w": 6614.5,
      "t20n": 6445.6,
      "t30w": 6303.1,
      "t30n": 6178.0,
      "top": 9244,
      "avg": 5269.9,
      "sum": 521721,
      "median": 5060.0,
      "threshold": 4444,
      "std": 743.8,
      "top10avg": 6908.9,
      "p25": 4717.0,
      "p75": 5662.5,
      "p90": 6066.2,
      "count": 99,
      "dist": {
        "8350": 1,
        "7550": 1,
        "7300": 1,
        "7150": 1,
        "6750": 1,
        "6700": 1,
        "6600": 1,
        "6200": 2,
        "6050": 4,
        "6000": 3,
        "5900": 2,
        "5850": 2,
        "5800": 1,
        "5750": 1,
        "5700": 1,
        "5650": 3,
        "5550": 1,
        "5500": 1,
        "5450": 5,
        "5400": 1,
        "5350": 1,
        "5300": 3,
        "5250": 2,
        "5200": 2,
        "5150": 2,
        "5100": 3,
        "5050": 3,
        "5000": 5,
        "4950": 3,
        "4900": 2,
        "4850": 3,
        "4800": 3,
        "4750": 3,
        "4700": 7,
        "4650": 3,
        "4600": 5,
        "4550": 3,
        "4500": 8,
        "4450": 3,
        "4400": 1
      },
      "games": 5516,
      "avgGameScore": 13.4
    }
  ],
  "gameStats": {
    "totalGames": 63404,
    "overallAvgGameScore": 24.8,
    "uniquePlayers": 2663,
    "avgGamesPerPlayer": 23.8
  }
}